pysmshub/__init__.py
pysmshub/asynchronous.py
pysmshub/base.py
pysmshub/exceptions.py
pysmshub/handlers.py
pysmshub/synchronous.py
pysmshub/utils.py
pysmshub-0.1.3.dist-info/licenses/LICENSE
pysmshub-0.1.3.dist-info/METADATA
pysmshub-0.1.3.dist-info/WHEEL
pysmshub-0.1.3.dist-info/top_level.txt
pysmshub-0.1.3.dist-info/RECORD
