Metadata-Version: 2.4
Name: pysmshub
Version: 0.1.3
Summary: A Python wrapper for the SmsHub API supporting synchronous and asynchronous requests.
Home-page: https://github.com/kuudori/pysmshub
Author: kuudori
Requires-Python: >=3.8
License-File: LICENSE
Requires-Dist: requests
Requires-Dist: aiohttp
Dynamic: author
Dynamic: description
Dynamic: description-content-type
Dynamic: home-page
Dynamic: license-file
Dynamic: requires-dist
Dynamic: requires-python
Dynamic: summary
